adafruit_mcp230xx/__init__.py
adafruit_mcp230xx/digital_inout.py
adafruit_mcp230xx/mcp23008.py
adafruit_mcp230xx/mcp23016.py
adafruit_mcp230xx/mcp23017.py
adafruit_mcp230xx/mcp230xx.py
adafruit_mcp230xx/mcp23s08.py
adafruit_mcp230xx/mcp23s17.py
adafruit_mcp230xx/mcp23sxx.py
adafruit_mcp230xx/mcp23xxx.py
adafruit_circuitpython_mcp230xx-2.5.14.dist-info/LICENSE
adafruit_circuitpython_mcp230xx-2.5.14.dist-info/METADATA
adafruit_circuitpython_mcp230xx-2.5.14.dist-info/WHEEL
adafruit_circuitpython_mcp230xx-2.5.14.dist-info/top_level.txt
adafruit_circuitpython_mcp230xx-2.5.14.dist-info/RECORD
