Metadata-Version: 2.1
Name: adafruit-circuitpython-mcp230xx
Version: 2.5.14
Summary: CircuitPython library for controlling a MCP23008 or MCP23017 I2C GPIO expander.
Author-email: Adafruit Industries <circuitpython@adafruit.com>
License: MIT
Project-URL: Homepage, https://github.com/adafruit/Adafruit_CircuitPython_MCP230xx
Keywords: adafruit,mcp23017,mcp23008,i2c,gpio,expander,hardware,micropython,circuitpython
Classifier: Intended Audience :: Developers
Classifier: Topic :: Software Development :: Libraries
Classifier: Topic :: Software Development :: Embedded Systems
Classifier: Topic :: System :: Hardware
Classifier: License :: OSI Approved :: MIT License
Classifier: Programming Language :: Python :: 3
License-File: LICENSE
Requires-Dist: Adafruit-Blinka
Requires-Dist: adafruit-circuitpython-busdevice
Provides-Extra: optional
